flask_restplus_sqlalchemy/__init__.py
flask_restplus_sqlalchemy/factory.py
test/__init__.py
test/test_factory.py
flask_restplus_sqlalchemy-0.0.3.dist-info/LICENSE
flask_restplus_sqlalchemy-0.0.3.dist-info/METADATA
flask_restplus_sqlalchemy-0.0.3.dist-info/WHEEL
flask_restplus_sqlalchemy-0.0.3.dist-info/top_level.txt
flask_restplus_sqlalchemy-0.0.3.dist-info/RECORD
