Metadata-Version: 2.1
Name: flask-restplus-sqlalchemy
Version: 0.0.3
Summary: Flask RestPlus SqlAlchemy
Home-page: https://bluemner.github.io/flask_restplus_sqlalchemy/
Author: Brandon Bluemner
License: UNKNOWN
Project-URL: Bug Reports, https://github.com/bluemner/flask_restplus_sqlalchemy/issues
Project-URL: Source, https://github.com/bluemner/flask_restplus_sqlalchemy
Keywords: flask restplus api sql SqlAlchemy swagger models
Platform: UNKNOWN
Classifier: Development Status :: 5 - Production/Stable
Classifier: Intended Audience :: Developers
Classifier: Framework :: Flask
Classifier: License :: OSI Approved :: MIT License
Classifier: Programming Language :: Python :: 3.5
Classifier: Programming Language :: Python :: 3.6
Classifier: Programming Language :: Python :: 3.7
Classifier: Programming Language :: Python :: 3.8
Requires-Python: >=3.5
Requires-Dist: SQLAlchemy
Requires-Dist: flask-restplus
Requires-Dist: flask-sqlalchemy
Provides-Extra: dev
Requires-Dist: bandit ; extra == 'dev'
Requires-Dist: coverage ; extra == 'dev'
Requires-Dist: pylint ; extra == 'dev'
Requires-Dist: pytest-cov ; extra == 'dev'
Requires-Dist: sphinx-theme ; extra == 'dev'
Provides-Extra: test
Requires-Dist: bandit ; extra == 'test'
Requires-Dist: coverage ; extra == 'test'
Requires-Dist: pylint ; extra == 'test'
Requires-Dist: pytest-cov ; extra == 'test'
Requires-Dist: sphinx-theme ; extra == 'test'
